gene_signature_survival/__init__.py
gene_signature_survival/core.py
gene_signature_survival-0.1.0.dist-info/licenses/LICENSE
gene_signature_survival-0.1.0.dist-info/METADATA
gene_signature_survival-0.1.0.dist-info/WHEEL
gene_signature_survival-0.1.0.dist-info/top_level.txt
gene_signature_survival-0.1.0.dist-info/RECORD
