Metadata-Version: 2.4
Name: gene-signature-survival
Version: 0.1.0
Summary: This packet includes modules to claculate sample scoring of gene signature, and analize clinical survival data using this scores
Author-email: Jahaciel Villaverde Nogues <jahacieljunior@gmail.com>, "Vall d'Hebron Institute of Oncology (Bioinformatics Unit)" <VHIOinformatics@vhio.net>
License: MIT License
Keywords: gene expression,survival analysis,singscore,survival_cutpoint,gene signature
Classifier: Programming Language :: Python :: 3
Classifier: License :: OSI Approved :: MIT License
Classifier: Operating System :: OS Independent
Requires-Python: >=3.9
License-File: LICENSE
Requires-Dist: pandas>=1.5
Requires-Dist: numpy>=1.24
Requires-Dist: matplotlib>=3.7
Requires-Dist: lifelines>=0.27
Requires-Dist: seaborn>=0.13
Dynamic: license-file
